{
  "name": "رزرو وقت - مکانیک لند",
  "short_name": "رزرو وقت",
  "description": "رزرو آنلاین وقت تعمیر خودرو در یزد - تعمیرگاه مکانیک لند",
  "start_url": "/booking.html",
  "scope": "/",
  "display": "standalone",
  "background_color": "#ffffff",
  "theme_color": "#000000",
  "orientation": "portrait-primary",
  "icons": [
    {
      "src": "/android-chrome-192x192.png",
      "sizes": "192x192",
      "type": "image/png",
      "purpose": "any maskable"
    },
    {
      "src": "/android-chrome-512x512.png",
      "sizes": "512x512",
      "type": "image/png",
      "purpose": "any maskable"
    }
  ],
  "categories": ["business", "productivity"],
  "lang": "fa",
  "dir": "rtl"
}

